{
  "meta": {
    "version": "1.2",
    "sceneName": "forest_level_1",
    "width": 720,
    "height": 1280,
    "backgroundColor": "#87CEEB",
    "backgroundImage": "assets/environment/sky_tiled.png",
    "backgroundMode": "tile",
    "physics": {
      "gravityX": 0,
      "gravityY": 9.8
    },
    "grid": {
      "enabled": true,
      "size": 64,
      "snap": false
    }
  },
  "library": {
    "sprites": {
      "hero_config": {
        "sourceFile": "assets/characters/hero_sheet.png",
        "frameWidth": 32,
        "frameHeight": 32,
        "animations": {
          "idle": {
            "frames": [
              0,
              1
            ],
            "loop": true,
            "fps": 4
          },
          "walk": {
            "frames": [
              2,
              3,
              4,
              5
            ],
            "loop": true,
            "fps": 10
          },
          "jump": {
            "frames": [
              6
            ],
            "loop": false,
            "fps": 1
          }
        }
      },
      "enemy_slime": {
        "sourceFile": "assets/enemies/slime.png",
        "frameWidth": 16,
        "frameHeight": 16,
        "animations": {
          "bounce": {
            "frames": [
              0,
              1,
              2,
              1
            ],
            "loop": true,
            "fps": 6
          }
        }
      }
    }
  },
  "objects": [
    {
      "id": "obj_1766938175165",
      "name": "office",
      "type": "static",
      "asset": "assets/background/empty.png",
      "parentId": null,
      "x": 0,
      "y": 0,
      "width": 728,
      "height": 1319.5,
      "opacity": 1,
      "zIndex": 0,
      "visible": true,
      "locked": true
    },
    {
      "id": "obj_1766938203325",
      "name": "drawers",
      "type": "static",
      "asset": "assets/furniture/drawers.png",
      "parentId": null,
      "x": -81.18120805369126,
      "y": 331.1677852348993,
      "width": 174.05317501290656,
      "height": 206.13123457159926,
      "opacity": 1,
      "zIndex": 0,
      "visible": true,
      "locked": false
    },
    {
      "id": "obj_1766938308975",
      "name": "desk",
      "type": "static",
      "asset": "assets/furniture/desk.png",
      "parentId": null,
      "x": 92.91846694692325,
      "y": 405.51472199686975,
      "width": 221.71794871794873,
      "height": 202.87506355778314,
      "opacity": 1,
      "zIndex": 1,
      "visible": true,
      "locked": false
    },
    {
      "id": "obj_1766938314800",
      "name": "picture",
      "type": "static",
      "asset": "assets/furniture/picture-frame.png",
      "parentId": null,
      "x": 224.068376068376,
      "y": 170.3931623931624,
      "width": 116.09401709401709,
      "height": 145.92823377739577,
      "opacity": 1,
      "zIndex": 0,
      "visible": true,
      "locked": false
    },
    {
      "id": "obj_1766938318527",
      "name": "plant",
      "type": "static",
      "asset": "assets/furniture/potted-plant.png",
      "parentId": null,
      "x": 158.42735042735035,
      "y": 304.4102564102564,
      "width": 78.12,
      "height": 111.11653429602887,
      "opacity": 1,
      "zIndex": 0,
      "visible": true,
      "locked": true
    },
    {
      "id": "obj_1766938961356",
      "name": "package1",
      "type": "static",
      "asset": "assets/parcels/package1.png",
      "parentId": "folder_1766939792322",
      "x": 421.65138677195324,
      "y": 42.571039889473596,
      "width": 125.44966442953023,
      "height": 142.1491327464482,
      "opacity": 1,
      "zIndex": 6,
      "visible": true,
      "locked": false
    },
    {
      "id": "obj_1766939205927",
      "name": "package2",
      "type": "static",
      "asset": "assets/parcels/package2.png",
      "parentId": "folder_1766939792322",
      "x": 499.95311245517325,
      "y": 265.3398276508055,
      "width": 139.94117647058818,
      "height": 120.98660789964394,
      "opacity": 1,
      "zIndex": 5,
      "visible": true,
      "locked": false
    },
    {
      "id": "obj_1766939244925",
      "name": "package6",
      "type": "static",
      "asset": "assets/parcels/package6.png",
      "parentId": "folder_1766939792322",
      "x": 426.4017556067011,
      "y": 167.4818819247444,
      "width": 90.3529411764705,
      "height": 174.51233396584422,
      "opacity": 1,
      "zIndex": 4,
      "visible": true,
      "locked": false
    },
    {
      "id": "folder_1766939792322",
      "name": "packages",
      "type": "folder",
      "parentId": null,
      "zIndex": 0,
      "visible": true,
      "locked": false
    },
    {
      "id": "obj_1767076924822",
      "name": "shelf-leg",
      "type": "static",
      "asset": "assets/furniture/shelf-leg.png",
      "parentId": "folder_1767079129879",
      "x": 331.4940855323021,
      "y": 220.725517298863,
      "width": 184.5195632393084,
      "height": 247.90414603143728,
      "opacity": 1,
      "zIndex": 1,
      "visible": true,
      "locked": true
    },
    {
      "id": "obj_1767077203537_535",
      "name": "shelf-leg_copy",
      "type": "static",
      "asset": "assets/furniture/shelf-leg.png",
      "parentId": "folder_1767079129879",
      "x": 331.6942675159236,
      "y": 50.880203377116004,
      "width": 184.5195632393084,
      "height": 247.90414603143728,
      "opacity": 1,
      "zIndex": 1,
      "visible": true,
      "locked": true
    },
    {
      "id": "obj_1767077219348_580",
      "name": "shelf-leg_copy",
      "type": "static",
      "asset": "assets/furniture/shelf-leg.png",
      "parentId": "folder_1767079129879",
      "x": 578.6096451319381,
      "y": 359.52442539713417,
      "width": 184.5195632393084,
      "height": 247.90414603143728,
      "opacity": 1,
      "zIndex": 5,
      "visible": true,
      "locked": true
    },
    {
      "id": "obj_1767077219348_354",
      "name": "shelf-leg_copy_copy",
      "type": "static",
      "asset": "assets/furniture/shelf-leg.png",
      "parentId": "folder_1767079129879",
      "x": 578.8098271155595,
      "y": 187.34972112051906,
      "width": 184.5195632393084,
      "height": 247.90414603143728,
      "opacity": 1,
      "zIndex": 6,
      "visible": true,
      "locked": true
    },
    {
      "id": "obj_1767077700658",
      "name": "shelf_1",
      "type": "static",
      "asset": "assets/furniture/shelf.png",
      "parentId": "folder_1767079129879",
      "x": 367.59963603275696,
      "y": 376.31983242792336,
      "width": 364.6396724294814,
      "height": 219.39081361393292,
      "opacity": 1,
      "zIndex": 1,
      "visible": true,
      "locked": true
    },
    {
      "id": "obj_1767077818188_726",
      "name": "shelf_2",
      "type": "static",
      "asset": "assets/furniture/shelf.png",
      "parentId": "folder_1767079129879",
      "x": 367.7998180163785,
      "y": 249.56824007123544,
      "width": 364.6396724294814,
      "height": 219.39081361393292,
      "opacity": 1,
      "zIndex": 3,
      "visible": true,
      "locked": true
    },
    {
      "id": "obj_1767077843975_128",
      "name": "shelf_3",
      "type": "static",
      "asset": "assets/furniture/shelf.png",
      "parentId": "folder_1767079129879",
      "x": 369.164695177434,
      "y": 92.53457310126277,
      "width": 364.6396724294814,
      "height": 219.39081361393292,
      "opacity": 1,
      "zIndex": 5,
      "visible": true,
      "locked": true
    },
    {
      "id": "obj_1767078917421",
      "name": "left-glass-fence",
      "type": "static",
      "asset": "assets/furniture/left-glass-fence.png",
      "parentId": "folder_1767079058867",
      "x": -20.24385805277518,
      "y": 493.1119803258111,
      "width": 404.1555959963604,
      "height": 404.7387931045802,
      "opacity": 0.5,
      "zIndex": 2,
      "visible": true,
      "locked": true
    },
    {
      "id": "obj_1767078938670",
      "name": "right-glass-fence",
      "type": "static",
      "asset": "assets/furniture/right-glass-fence.png",
      "parentId": "folder_1767079058867",
      "x": 352.4585987261146,
      "y": 515.4017702043179,
      "width": 407.00272975432216,
      "height": 390.2369923070561,
      "opacity": 0.5,
      "zIndex": 7,
      "visible": true,
      "locked": true
    },
    {
      "id": "folder_1767079058867",
      "name": "glass fence",
      "type": "folder",
      "parentId": null,
      "zIndex": 0,
      "visible": true,
      "locked": false
    },
    {
      "id": "folder_1767079129879",
      "name": "shelves",
      "type": "folder",
      "parentId": null,
      "zIndex": 0,
      "visible": true,
      "locked": false
    },
    {
      "id": "obj_1767079264645",
      "name": "package8",
      "type": "static",
      "asset": "assets/parcels/package8.png",
      "parentId": "folder_1766939792322",
      "x": 525.4857142857143,
      "y": 369.4339977264115,
      "width": 142.94285714285712,
      "height": 163.417430845017,
      "opacity": 1,
      "zIndex": 2,
      "visible": true,
      "locked": false
    },
    {
      "id": "obj_1767088717343",
      "name": "boy-1-back-right-with-box",
      "type": "static",
      "asset": "assets/people/boy-1-back-right-with-box.png",
      "parentId": "folder_1767091011506",
      "x": 112.96,
      "y": 427.5931428571428,
      "width": 129.37142857142857,
      "height": 201.17257142857142,
      "opacity": 1,
      "zIndex": 2,
      "visible": true,
      "locked": false
    },
    {
      "id": "obj_1767088756293",
      "name": "man-1-back-right",
      "type": "static",
      "asset": "assets/people/man-1-back-right.png",
      "parentId": "folder_1767091011506",
      "x": 52.9828571428571,
      "y": 449.1006820276497,
      "width": 106.66285714285715,
      "height": 207.4764608294931,
      "opacity": 1,
      "zIndex": 2,
      "visible": true,
      "locked": false
    },
    {
      "id": "obj_1767088824383",
      "name": "boy-2-back-right-with-box",
      "type": "static",
      "asset": "assets/people/boy-2-back-right-with-box.png",
      "parentId": "folder_1767091011506",
      "x": -17.234285714285612,
      "y": 492.73680291380026,
      "width": 118.94285714285715,
      "height": 207.5603399433428,
      "opacity": 1,
      "zIndex": 2,
      "visible": true,
      "locked": false
    },
    {
      "id": "obj_1767088785628",
      "name": "woman-sitting-on-chair",
      "type": "static",
      "asset": "assets/people/woman-sitting-on-chair.png",
      "parentId": "folder_1767091011506",
      "x": 191.95428571428565,
      "y": 358.259911353563,
      "width": 160.07428571428568,
      "height": 222.7286600750085,
      "opacity": 1,
      "zIndex": 0,
      "visible": true,
      "locked": false
    },
    {
      "id": "obj_1767088858456",
      "name": "woman-1-with-box",
      "type": "static",
      "asset": "assets/people/woman-1-with-box.png",
      "parentId": "folder_1767091011506",
      "x": 532.8000000000001,
      "y": 517.3425009678668,
      "width": 137.86857142857144,
      "height": 249.58321331784748,
      "opacity": 1,
      "zIndex": 4,
      "visible": true,
      "locked": false
    },
    {
      "id": "folder_1767090490469",
      "name": "drones",
      "type": "folder",
      "parentId": null,
      "zIndex": 0,
      "visible": true,
      "locked": false
    },
    {
      "id": "obj_1767090496428",
      "name": "launch-pad",
      "type": "static",
      "asset": "assets/drones/launch-pad.png",
      "parentId": "folder_1767090532605",
      "x": 189.02857142857138,
      "y": 948.8457142857144,
      "width": 190.37142857142868,
      "height": 119.34347691354208,
      "opacity": 1,
      "zIndex": 1,
      "visible": true,
      "locked": false
    },
    {
      "id": "folder_1767090532605",
      "name": "launch-pads",
      "type": "folder",
      "parentId": null,
      "zIndex": 0,
      "visible": true,
      "locked": false
    },
    {
      "id": "obj_1767090539879",
      "name": "drone-1",
      "type": "static",
      "asset": "assets/drones/drone-1.png",
      "parentId": "folder_1767090490469",
      "x": 371.8857142857143,
      "y": 1010.8107704962981,
      "width": 191.85714285714278,
      "height": 122.25829448862073,
      "opacity": 1,
      "zIndex": 2,
      "visible": true,
      "locked": false
    },
    {
      "id": "obj_1767090545879",
      "name": "drone-2",
      "type": "static",
      "asset": "assets/drones/drone-2.png",
      "parentId": "folder_1767090490469",
      "x": 219.74857142857155,
      "y": 1115.4262567811936,
      "width": 190.20571428571435,
      "height": 111.95652802893314,
      "opacity": 1,
      "zIndex": 2,
      "visible": true,
      "locked": false
    },
    {
      "id": "obj_1767090549600",
      "name": "drone-3",
      "type": "static",
      "asset": "assets/drones/drone-3.png",
      "parentId": "folder_1767090490469",
      "x": 210.9714285714287,
      "y": 924.5967414403776,
      "width": 140.2285714285714,
      "height": 101.69468713105074,
      "opacity": 1,
      "zIndex": 2,
      "visible": true,
      "locked": false
    },
    {
      "id": "obj_1767090551925",
      "name": "drone-4",
      "type": "static",
      "asset": "assets/drones/drone-4.png",
      "parentId": "folder_1767090490469",
      "x": 50.05714285714281,
      "y": 997.8142807105332,
      "width": 162.86285714285708,
      "height": 115.51568676507377,
      "opacity": 1,
      "zIndex": 2,
      "visible": true,
      "locked": false
    },
    {
      "id": "folder_1767090569154",
      "name": "batteries",
      "type": "folder",
      "parentId": null,
      "zIndex": 0,
      "visible": true,
      "locked": false
    },
    {
      "id": "obj_1767090578356",
      "name": "battery-charger",
      "type": "static",
      "asset": "assets/batteries/battery-charger.png",
      "parentId": "folder_1767090569154",
      "x": 570.8342857142857,
      "y": 866.8374130497269,
      "width": 83.0114285714285,
      "height": 123.43148031043391,
      "opacity": 1,
      "zIndex": 0,
      "visible": true,
      "locked": false
    },
    {
      "id": "obj_1767090585639",
      "name": "battery-shelf-wall",
      "type": "static",
      "asset": "assets/batteries/battery-shelf-wall.png",
      "parentId": "folder_1767090569154",
      "x": 357.25714285714275,
      "y": 746.7602945508098,
      "width": 75.96000000000004,
      "height": 195.25113402061865,
      "opacity": 1,
      "zIndex": 0,
      "visible": true,
      "locked": false
    },
    {
      "id": "obj_1767090590988",
      "name": "battery-shelf_1",
      "type": "static",
      "asset": "assets/batteries/battery-shelf.png",
      "parentId": "folder_1767090569154",
      "x": 368.9600000000001,
      "y": 774.6635294117648,
      "width": 216,
      "height": 133.67647058823528,
      "opacity": 1,
      "zIndex": 0,
      "visible": true,
      "locked": false
    },
    {
      "id": "obj_1767090863971_112",
      "name": "battery-1_copy",
      "type": "static",
      "asset": "assets/batteries/battery-1.png",
      "parentId": "folder_1767090569154",
      "x": 448.9371428571428,
      "y": 756.880884564352,
      "width": 67,
      "height": 97.28482972136223,
      "opacity": 1,
      "zIndex": 0,
      "visible": true,
      "locked": false
    },
    {
      "id": "obj_1767090582248",
      "name": "battery-1",
      "type": "static",
      "asset": "assets/batteries/battery-1.png",
      "parentId": "folder_1767090569154",
      "x": 484.5257142857143,
      "y": 776.378027421495,
      "width": 67,
      "height": 97.28482972136223,
      "opacity": 1,
      "zIndex": 0,
      "visible": true,
      "locked": false
    },
    {
      "id": "obj_1767090589246",
      "name": "battery-shelf",
      "type": "static",
      "asset": "assets/batteries/battery-shelf.png",
      "parentId": "folder_1767090569154",
      "x": 370.42285714285714,
      "y": 857.6268907563024,
      "width": 216,
      "height": 133.67647058823528,
      "opacity": 1,
      "zIndex": 0,
      "visible": true,
      "locked": false
    },
    {
      "id": "obj_1767090776547_270",
      "name": "launch-pad_copy",
      "type": "static",
      "asset": "assets/drones/launch-pad.png",
      "parentId": "folder_1767090532605",
      "x": 371.4057142857142,
      "y": 1044.914285714286,
      "width": 190.37142857142868,
      "height": 119.34347691354208,
      "opacity": 1,
      "zIndex": 0,
      "visible": true,
      "locked": false
    },
    {
      "id": "obj_1767090780439_937",
      "name": "launch-pad_copy_copy",
      "type": "static",
      "asset": "assets/drones/launch-pad.png",
      "parentId": "folder_1767090532605",
      "x": 226.1028571428571,
      "y": 1139.5200000000002,
      "width": 190.37142857142868,
      "height": 119.34347691354208,
      "opacity": 1,
      "zIndex": 0,
      "visible": true,
      "locked": false
    },
    {
      "id": "obj_1767090785531_593",
      "name": "launch-pad_copy",
      "type": "static",
      "asset": "assets/drones/launch-pad.png",
      "parentId": "folder_1767090532605",
      "x": 29.097142857142828,
      "y": 1034.6742857142858,
      "width": 190.37142857142868,
      "height": 119.34347691354208,
      "opacity": 1,
      "zIndex": 0,
      "visible": true,
      "locked": false
    },
    {
      "id": "obj_1767090587731",
      "name": "battery-shelf-wall_1",
      "type": "static",
      "asset": "assets/batteries/battery-shelf-wall.png",
      "parentId": "folder_1767090569154",
      "x": 515.2457142857143,
      "y": 834.7378301423663,
      "width": 73.03428571428566,
      "height": 187.73074128620507,
      "opacity": 1,
      "zIndex": 3,
      "visible": true,
      "locked": false
    },
    {
      "id": "folder_1767091011506",
      "name": "people",
      "type": "folder",
      "parentId": null,
      "zIndex": 0,
      "visible": true,
      "locked": false
    }
  ]
}